health_universe_sdk/__init__.py
health_universe_sdk/cli.py
health_universe_sdk/repo_utils.py
health_universe_sdk-0.1.2.dist-info/METADATA
health_universe_sdk-0.1.2.dist-info/WHEEL
health_universe_sdk-0.1.2.dist-info/entry_points.txt
health_universe_sdk-0.1.2.dist-info/RECORD
