Metadata-Version: 2.4
Name: health-universe-sdk
Version: 0.1.2
Summary: Health Universe SDK
Project-URL: Homepage, https://github.com/Health-Universe/health-universe-sdk
Project-URL: Bug Tracker, https://github.com/Health-Universe/health-universe-sdk/issues
Author-email: "Greyson R. LaLonde" <greyson.lalonde@healthuniverse.com>
Classifier: License :: OSI Approved :: MIT License
Classifier: Operating System :: OS Independent
Classifier: Programming Language :: Python :: 3
Requires-Python: >=3.10
Requires-Dist: click>=8.0.0
